{"fecha_hora":{"creado":"2022-03-24 22:54:26"},"0":{"sesion":{"archivo":"127.0.0.1_2022-03-24_22_54_26.json"}},"1":{"cookie":[]},"2":{"request":{"action":"wp_1_wc_privacy_cleanup","nonce":"9e84ce90e3","0":{"task":"trash_pending_orders"},"1":{"task":"trash_failed_orders"},"2":{"task":"trash_cancelled_orders"},"3":{"task":"anonymize_completed_orders"},"4":{"task":"delete_inactive_accounts"},"5":{"task":"trash_pending_orders"},"6":{"task":"trash_failed_orders"},"7":{"task":"trash_cancelled_orders"},"8":{"task":"anonymize_completed_orders"},"9":{"task":"delete_inactive_accounts"}}}}